brisksec_toolbox_data_api_sdk/__init__.py
brisksec_toolbox_data_api_sdk/client.py
brisksec_toolbox_data_api_sdk/errors.py
brisksec_toolbox_data_api_sdk/py.typed
brisksec_toolbox_data_api_sdk/types.py
brisksec_toolbox_data_api_sdk/api/__init__.py
brisksec_toolbox_data_api_sdk/api/default/__init__.py
brisksec_toolbox_data_api_sdk/api/default/health_check_health_get.py
brisksec_toolbox_data_api_sdk/api/default/root_get.py
brisksec_toolbox_data_api_sdk/api/domains/__init__.py
brisksec_toolbox_data_api_sdk/api/domains/create_domain.py
brisksec_toolbox_data_api_sdk/api/domains/delete_domain.py
brisksec_toolbox_data_api_sdk/api/domains/get_domain.py
brisksec_toolbox_data_api_sdk/api/domains/get_domain_relationships.py
brisksec_toolbox_data_api_sdk/api/domains/get_expiring_domains.py
brisksec_toolbox_data_api_sdk/api/domains/list_domains.py
brisksec_toolbox_data_api_sdk/api/domains/update_domain.py
brisksec_toolbox_data_api_sdk/api/ip_addresses/__init__.py
brisksec_toolbox_data_api_sdk/api/ip_addresses/create_ipaddress.py
brisksec_toolbox_data_api_sdk/api/ip_addresses/delete_ipaddress.py
brisksec_toolbox_data_api_sdk/api/ip_addresses/get_ipaddress.py
brisksec_toolbox_data_api_sdk/api/ip_addresses/get_ipaddress_relationships.py
brisksec_toolbox_data_api_sdk/api/ip_addresses/list_ip_addresses.py
brisksec_toolbox_data_api_sdk/api/ip_addresses/update_ipaddress.py
brisksec_toolbox_data_api_sdk/api/organizations/__init__.py
brisksec_toolbox_data_api_sdk/api/organizations/create_organization.py
brisksec_toolbox_data_api_sdk/api/organizations/delete_organization.py
brisksec_toolbox_data_api_sdk/api/organizations/get_organization.py
brisksec_toolbox_data_api_sdk/api/organizations/get_organization_relationships.py
brisksec_toolbox_data_api_sdk/api/organizations/list_organizations.py
brisksec_toolbox_data_api_sdk/api/organizations/update_organization.py
brisksec_toolbox_data_api_sdk/api/relationships/__init__.py
brisksec_toolbox_data_api_sdk/api/relationships/create_relationship.py
brisksec_toolbox_data_api_sdk-1.2025.610.1108.dist-info/METADATA
brisksec_toolbox_data_api_sdk-1.2025.610.1108.dist-info/WHEEL
brisksec_toolbox_data_api_sdk-1.2025.610.1108.dist-info/licenses/LICENSE
brisksec_toolbox_data_api_sdk-1.2025.610.1108.dist-info/RECORD
