Metadata-Version: 2.4
Name: brisksec_toolbox_data_api_sdk
Version: 1.2025.610.1108
Summary: Official Python SDK for the BriskSec Toolbox Data API
Project-URL: Homepage, https://github.com/brisksec/brisksec-toolbox-data-api-sdk
Project-URL: Repository, https://github.com/brisksec/brisksec-toolbox-data-api-sdk
Project-URL: Documentation, https://brisksec.github.io/brisksec-toolbox-data-api-sdk
Project-URL: Bug Reports, https://github.com/brisksec/brisksec-toolbox-data-api-sdk/issues
Author-email: BriskSec Team <dev@brisksec.com>
License-Expression: MIT
License-File: LICENSE
Keywords: api,brisksec,data,sdk,security,toolbox
Classifier: Development Status :: 4 - Beta
Classifier: Intended Audience :: Developers
Classifier: License :: OSI Approved :: MIT License
Classifier: Programming Language :: Python :: 3
Classifier: Programming Language :: Python :: 3.9
Classifier: Programming Language :: Python :: 3.10
Classifier: Programming Language :: Python :: 3.11
Classifier: Programming Language :: Python :: 3.12
Classifier: Topic :: Internet :: WWW/HTTP :: HTTP Servers
Classifier: Topic :: Security
Classifier: Topic :: Software Development :: Libraries :: Python Modules
Requires-Python: >=3.9
Requires-Dist: attrs>=22.2.0
Requires-Dist: httpx>=0.20.0
Requires-Dist: python-dateutil>=2.8.0
Provides-Extra: dev
Requires-Dist: black; extra == 'dev'
Requires-Dist: build; extra == 'dev'
Requires-Dist: flake8; extra == 'dev'
Requires-Dist: isort; extra == 'dev'
Requires-Dist: mypy; extra == 'dev'
Requires-Dist: pytest-asyncio; extra == 'dev'
Requires-Dist: pytest-cov; extra == 'dev'
Requires-Dist: pytest>=6.0; extra == 'dev'
Requires-Dist: twine; extra == 'dev'
